README.md
setup.py
src/wxw/__init__.py
src/wxw/camera_helper.py
src/wxw/common.py
src/wxw/console_helper.py
src/wxw/cv_helper.py
src/wxw/face_helper.py
src/wxw/file.py
src/wxw/gaze_helper.py
src/wxw/gradio_helper.py
src/wxw/onnx_helper.py
src/wxw/openai_helper.py
src/wxw/qt5_helper.py
src/wxw/seed_helper.py
src/wxw/tracker.py
src/wxw/trainer_helper.py
src/wxw/utils.py
src/wxw/yolo_helper.py
src/wxw.egg-info/PKG-INFO
src/wxw.egg-info/SOURCES.txt
src/wxw.egg-info/dependency_links.txt
src/wxw.egg-info/entry_points.txt
src/wxw.egg-info/requires.txt
src/wxw.egg-info/top_level.txt
src/wxw/scripts/__init__.py
src/wxw/scripts/baidu_spider.py
src/wxw/scripts/calibrate_camera.py
src/wxw/scripts/fix_vscode_jump.py
src/wxw/scripts/roop_face.py